<Festival>
	<Events>
		<Event>
			<Date>
				<WeekDay>Friday</WeekDay>
				<Day>20</Day>
				<Month>April</Month>
			</Date>
			<Classes>	
				<Class>
					<Name>Beginner's Crash Course</Name>
					<Teachers>Jake &amp; Dasha</Teachers>
					<Level>Beg</Level>
					<StartTime>1800</StartTime>
					<EndTime>1930</EndTime>
					<Room>Atrium</Room>
				</Class>
				<Class>
					<Name>Villa Urquiza</Name>
					<Teachers>Ney &amp; Rosa</Teachers>
					<Level>Int</Level>
					<StartTime>1730</StartTime>
					<EndTime>1900</EndTime>
					<Room>Prince Georges</Room>
				</Class>
				<Class>
					<Name>Musicality for Romantic &amp; Dramatic Music</Name>
					<Teachers>Ney &amp; Rosa</Teachers>
					<Level>Int</Level>
					<StartTime>2000</StartTime>
					<EndTime>2130</EndTime>
					<Room>Prince Georges</Room>
				</Class>
			</Classes>
			<Milonga>
				<Name>The Start of a Journey Milonga</Name>
				<StartTime>2100</StartTime>
				<EndTime>100</EndTime>
			</Milonga>
		</Event>
		<Event>
			<Date>
				<WeekDay>Saturday</WeekDay>
				<Day>21</Day>
				<Month>April</Month>
			</Date>
			<Classes>
				<Class>	
					<Name>Cross-System Ninjas: Become masters of stealth and dexterity in cross-system</Name>
					<Teachers>Eric &amp; Rebecca</Teachers>
					<Level>Int</Level>
					<StartTime>1400</StartTime>
					<EndTime>1530</EndTime>
					<Room>Prince Georges</Room>
				</Class>
			</Classes>
			<Milonga>
				<Name>The Grand Milonga</Name>
				<StartTime>2100</StartTime>
				<EndTime>130</EndTime>
			</Milonga>
		</Event>
		<Event>
			<Date>
				<WeekDay>Sunday</WeekDay>
				<Day>22</Day>
				<Month>April</Month>
			</Date>
			<Classes>
				<Class>	
					<Name>Paradas and cruzadas</Name>
					<Teachers>Ney &amp; Rosa</Teachers>
					<Level>Int/Adv</Level>
					<StartTime>1200</StartTime>
					<EndTime>1330</EndTime>
					<Room>Atrium</Room>
				</Class>
				<Class>	
					<Name>Complex figures to the left: Understanding continuity and flow through classical combinations</Name>
					<Teachers>Eric &amp; Rebecca</Teachers>
					<Level>Int/Adv</Level>
					<StartTime>1400</StartTime>
					<EndTime>1530</EndTime>
					<Room>Prince Georges</Room>
				</Class>
			</Classes>
			<Milonga>
				<Name>Last Dance Milonga</Name>
				<StartTime>2030</StartTime>
				<EndTime>000</EndTime>
			</Milonga>
		</Event>
	</Events>
	<Prices>
		<UmdGmuStudent>
			<SpecialPasses>
				<FullPass>70</FullPass>
				<FridayPass>30</FridayPass>
				<SaturdayPass>40</SaturdayPass>
				<SundayPass>35</SundayPass>
				<MilongaPass>35</MilongaPass>
			</SpecialPasses>
			<SingleClass>35</SingleClass>
			<Milongas>
				<Friday>0</Friday>
				<Saturday>0</Saturday>
				<Sunday>0</Sunday>
			</Milongas>
		</UmdGmuStudent>
		<OtherStudent>
			<SpecialPasses>
				<FullPass>70</FullPass>
				<FridayPass>30</FridayPass>
				<SaturdayPass>40</SaturdayPass>
				<SundayPass>35</SundayPass>
				<MilongaPass>35</MilongaPass>
			</SpecialPasses>
			<SingleClass>35</SingleClass>
			<Milongas>
				<Friday>5</Friday>
				<Saturday>5</Saturday>
				<Sunday>5</Sunday>
			</Milongas>
		</OtherStudent>
		<GeneralAdmission>
			<SpecialPasses>
				<FullPass>100</FullPass>
				<FridayPass>50</FridayPass>
				<SaturdayPass>80</SaturdayPass>
				<SundayPass>45</SundayPass>
				<MilongaPass>45</MilongaPass>
			</SpecialPasses>
			<SingleClass>40</SingleClass>
			<Milongas>
				<Friday>10</Friday>
				<Saturday>10</Saturday>
				<Sunday>10</Sunday>
			</Milongas>
		</GeneralAdmission>
	</Prices>
</Festival>
